immobilus/__init__.py
immobilus/logic.py
immobilus-1.5.0.dist-info/LICENSE
immobilus-1.5.0.dist-info/METADATA
immobilus-1.5.0.dist-info/WHEEL
immobilus-1.5.0.dist-info/top_level.txt
immobilus-1.5.0.dist-info/RECORD
