Metadata-Version: 2.1
Name: immobilus
Version: 1.5.0
Summary: Say `Immobilus!` to freeze your tests
Home-page: https://github.com/pokidovea/immobilus
Author: Eugene Pokidov
Author-email: pokidovea@gmail.com
License: Apache 2.0
Platform: UNKNOWN
Classifier: License :: OSI Approved :: Apache Software License
Classifier: Programming Language :: Python :: 3
Classifier: Programming Language :: Python :: 3.5
Classifier: Programming Language :: Python :: 3.6
Classifier: Programming Language :: Python :: 3.7
Classifier: Programming Language :: Python :: 3.8
Classifier: Programming Language :: Python :: 3.9
Classifier: Programming Language :: Python :: 3.10
Requires-Dist: python-dateutil
